{
  "kind": "collectionType",
  "collectionName": "case_studies",
  "info": {
    "singularName": "case-study",
    "pluralName": "case-studies",
    "displayName": "Case Study",
    "description": "Casos de éxito con información detallada del proyecto"
  },
  "options": {
    "draftAndPublish": true
  },
  "pluginOptions": {},
  "attributes": {
    "title": {
      "type": "string",
      "required": true,
      "maxLength": 255,
      "minLength": 1
    },
    "slug": {
      "type": "uid",
      "targetField": "title",
      "required": true
    },
    "summary": {
      "type": "text",
      "required": true,
      "maxLength": 500,
      "minLength": 1
    },
    "coverImage": {
      "type": "media",
      "multiple": false,
      "required": false,
      "allowedTypes": ["images"]
    },
    "gallery": {
      "type": "media",
      "multiple": true,
      "required": false,
      "allowedTypes": ["images"]
    },
    "clientName": {
      "type": "string",
      "required": true,
      "maxLength": 200
    },
    "clientLogo": {
      "type": "media",
      "multiple": false,
      "required": false,
      "allowedTypes": ["images"]
    },
    "location": {
      "type": "string",
      "required": false,
      "maxLength": 200
    },
    "industry": {
      "type": "relation",
      "relation": "manyToOne",
      "target": "api::case-industry.case-industry",
      "inversedBy": "case_studies"
    },
    "services": {
      "type": "relation",
      "relation": "manyToMany",
      "target": "api::case-service.case-service",
      "mappedBy": "case_studies"
    },
    "tags": {
      "type": "relation",
      "relation": "manyToMany",
      "target": "api::tag.tag",
      "mappedBy": "case_studies"
    },
    "metrics": {
      "type": "component",
      "repeatable": true,
      "component": "shared.case-metric"
    },
    "content": {
      "type": "richtext",
      "required": true
    },
    "featured": {
      "type": "boolean",
      "default": false,
      "required": false
    },
    "seo": {
      "type": "component",
      "repeatable": false,
      "component": "shared.seo"
    }
  }
}

